slurm_util/__init__.py
slurm_util/attach.py
slurm_util/py.typed
slurm_util/submit.py
slurm_util/utils.py
slurm_util-0.2.8.dist-info/METADATA
slurm_util-0.2.8.dist-info/WHEEL
slurm_util-0.2.8.dist-info/entry_points.txt
slurm_util-0.2.8.dist-info/RECORD
