Metadata-Version: 2.4
Name: slurm-util
Version: 0.2.8
Summary: Slurm utility functions
Author-email: Johan Edstedt <johan.edstedt@liu.se>
Requires-Python: >=3.8
